{
  "Individual": "व्यक्तिगत",
  "Business": "व्यवसाय",
  "Setting": "सेटिंग",
  "PocketPi": "पॉकेट पाई",
  "verify": "सत्यापित करें",
  "Copy": "कॉपी करें",
  "CurrentBalance": "वर्तमान शेष राशि",
  "TransactionHistory": "लेन-देन इतिहास",
  "expense": "खर्च",
  "Settings": "सेटिंग्स",
  "AddressBook": "पता पुस्तिका",
  "Subscription": "सदस्यता",
  "UpgradeToBusinessVersion": "व्यवसाय संस्करण में अपग्रेड करें",
  "PaymentRequest": "भुगतान अनुरोध",
  "WalletAddressBook": "वॉलेट पता पुस्तिका",
  "RecoverPin": "पिन पुनः प्राप्त करें",
  "FeedbackAndComplaint": "प्रतिक्रिया और शिकायत",
  "Save": "सहेजें",
  "Submit": "जमा करें",
  "CopiedToclipboard!": "क्लिपबोर्ड पर कॉपी किया गया!",
  "NoWalletAddressesFound": "कोई वॉलेट पता नहीं मिला",
  "EditWalletAddress": "वॉलेट पता संपादित करें",
  "AddWalletAddress": "वॉलेट पता जोड़ें",
  "WalletAddressmustbeAtLeast3Characters": "वॉलेट पता कम से कम 3 अक्षर का होना चाहिए",
  "WalletAddressIsRequired": "वॉलेट पता आवश्यक है",
  "WalletAddress": "वॉलेट पता",
  "EnterWalletAddress": "वॉलेट पता दर्ज करें",
  "AreYouSure": "क्या आप सुनिश्चित हैं?",
  "Paste": "चिपकाएं",
  "Cancel": "रद्द करें",
  "Delete": "हटाएं",
  "AreYouSureYouWantToDeleteWalletAddressRecords": "क्या आप वाकई वॉलेट पते के रिकॉर्ड को हटाना चाहते हैं?",
  "Type": "प्रकार",
  "Name": "नाम",
  "Username": "उपयोगकर्ता नाम",
  "UsernameCopiedToClipboard": "उपयोगकर्ता नाम क्लिपबोर्ड पर कॉपी किया गया!",
  "NoAddressDataFound": "कोई पता डेटा नहीं मिला",
  "AddAddress": "पता जोड़ें",
  "TypeRequired": "प्रकार आवश्यक है",
  "NameRequired": "नाम आवश्यक है",
  "NameSpace": "नाम की शुरुआत या अंत में स्पेस नहीं हो सकता",
  "UsernameRequired": "उपयोगकर्ता नाम आवश्यक है",
  "UsernameSpace": "उपयोगकर्ता नाम में स्पेस नहीं हो सकता",
  "Enter": "दर्ज करें",
  "DeleteRecords": "क्या आप वाकई पता रिकॉर्ड हटाना चाहते हैं?",
  "Send": "भेजें",
  "Receive": "प्राप्त करें",
  "Money": "पैसा",
  "Withdraw": "निकालें",
  "Deposit": "जमा करें",
  "Back": "वापस",
  "Subscribed": "सदस्यता ली गई",
  "Oky": "ठीक है",
  "Sent": "भेजा गया",
  "RequestBy": "अनुरोधकर्ता",
  "Amount": "राशि",
  "Description": "विवरण",
  "Status": "स्थिति",
  "Date": "तारीख",
  "Pay": "भुगतान करें",
  "Paid": "भुगतान किया गया",
  "Add": "जोड़ें",
  "Edit": "संपादित करें",
  "NoPayment": "कोई भुगतान अनुरोध प्राप्त नहीं हुआ",
  "NoPaymentSent": "कोई भुगतान भेजा गया अनुरोध नहीं मिला",
  "IsRequired": "आवश्यक है",
  "PurchaseSubscription": "3.14 Pi में एक सदस्यता खरीदें और बिना शुल्क के लेन-देन प्राप्त करें",
  "SomethingWrong": "कुछ गलत हो गया",
  "AnUnexpectedErrorOccurred": "एक अप्रत्याशित त्रुटि हुई",
  "UserNotExist": "दर्ज किया गया उपयोगकर्ता नाम मौजूद नहीं है",
  "Memo": "मेमो",
  "EnterPiAmount": "Pi राशि दर्ज करें",
  "SendPi": "Pi भेजें",
  "Pi": "Pi",
  "EnterName": "नाम दर्ज करें",
  "EnterUserName": "यूज़र नाम दर्ज करें",
  "EnterWalletAddress": "वॉलेट पता दर्ज करें",
  "EnterAmount": "राशि दर्ज करें",
  "EnterDescription": "विवरण दर्ज करें",
  "EnterMemo": "मेमो दर्ज करें",
  "OnlyDigitsAllowed": "केवल अंक की अनुमति है",
  "PleaseEnterPin": "कृपया पिन दर्ज करें",
  "PINDigits": "पिन 5 अंकों का होना चाहिए",
  "PleaseConformPin": "कृपया पुष्टि पिन दर्ज करें",
  "PINNotMatch": "पिन मेल नहीं खा रहा",
  "Icon": "आइकन",
  "Set": "सेट करें",
  "TransactionPIN": "लेनदेन पिन",
  "EnterPIN": "पिन दर्ज करें",
  "Next": "अगला",
  "SetPIN": "पिन सेट करें",
  "ConfirmPIN": "पिन की पुष्टि करें",
  "AvailableBalance": "उपलब्ध शेष राशि",
  "DeductFees": "लेनदेन शुल्क के रूप में काटा जाएगा",
  "Processing": "प्रोसेस हो रहा है...",
  "PleaseEnterPIN": "कृपया पिन दर्ज करें",
  "VerifyPIN": "पिन सत्यापित करें",
  "Verify": "सत्यापित करें",
  "Custom": "कस्टम",
  "SecurityQuestion": "सुरक्षा प्रश्न",
  "EnterYourAnswer": "अपना उत्तर दर्ज करें",
  "SecurityNotFound": "सुरक्षा प्रश्न नहीं मिला",
  "UpgradeVersion": "बिजनेस संस्करण में अपग्रेड करें",
  "EnterBusinessName": "व्यवसाय का नाम दर्ज करें",
  "EnterAnswer": "कृपया अपना उत्तर दर्ज करें",
  "EnterQuestion": "अपना कस्टम प्रश्न दर्ज करें",
  "EnterCustomeQuestion": "कृपया अपना कस्टम प्रश्न दर्ज करें",
  "QuestionAlreasyExist": "यह प्रश्न पहले से मौजूद है। कृपया एक अलग प्रश्न दर्ज करें",
  "ForPIN": "आपकी सुरक्षा के लिए, कृपया इस लेनदेन को जारी रखने के लिए अपना 5-अंकीय पिन दर्ज करें।",
  "PINContaint": "आपका पिन PocketPie के साथ सुरक्षित रूप से सहेजा जाएगा। ऐप में भुगतान करते समय आपको हर बार यह पिन दर्ज करना होगा।",
  "Share": "साझा करें",
  "ShareQRCode": "क्यूआर कोड साझा करें",
  "QRCode": "क्यूआर कोड",
  "Mainnet": "मुख्य नेटवर्क",
  "Download": "डाउनलोड करें",
  "QRCopy": "क्यूआर कोड लिंक सफलतापूर्वक कॉपी किया गया",
  "SharingFiels": "इस डिवाइस पर फ़ाइल साझा करना समर्थित नहीं है",
  "PleaseEnterUserName": "कृपया उपयोगकर्ता नाम दर्ज करें",
  "PleaseEnterAmount": "कृपया राशि दर्ज करें",
  "PleaseEnterAmountAtLeast": "राशि कम से कम 0.001 होनी चाहिए",
  "PleaseEnterAmountAtLeaseMust": "राशि कम से कम 0.05 होनी चाहिए",
  "PleaseEnterAmountAtLeaseMust1": "राशि कम से कम 0.01 होनी चाहिए",
  "PleaseEnterWallet": "कृपया वॉलेट पता दर्ज करें",
  "PleaseEnterWalletAddress": "कृपया वॉलेट पता दर्ज करें",
  "PleaseEnterBusinessName": "कृपया व्यवसाय का नाम दर्ज करें",
  "PleaseEnterMemo": "कृपया मेमो दर्ज करें",
  "YourTransactionWasSuccessful": "आपका लेन-देन सफल रहा",
  "GoToHome": "होम पर जाएं"
}
